README
setup.py
test_tools/__init__.py
test_tools/dprovider.py
test_tools/fixtureman.py
test_tools.egg-info/PKG-INFO
test_tools.egg-info/SOURCES.txt
test_tools.egg-info/dependency_links.txt
test_tools.egg-info/top_level.txt
test_tools.egg-info/zip-safe