Metadata-Version: 1.1
Name: test-tools
Version: 0.0.2
Summary: Tools for unit testing: data_provider and FixtureManager
Home-page: https://github.com/ygavenchuk/test-tools
Author: y.gavenchuk aka murminathor
Author-email: murminathor@gmail.com
License: Apache2
Platform: UNKNOWN
Classifier: Development Status :: 5 - Production/Stable
Classifier: Intended Audience :: Developers
Classifier: License :: OSI Approved :: Apache Software License
Classifier: Topic :: Software Development :: Testing
Classifier: Topic :: Software Development :: Libraries
Classifier: Programming Language :: Python :: 2.7
Classifier: Programming Language :: Python :: 3.2
Classifier: Programming Language :: Python :: 3.4
Classifier: Programming Language :: Python :: Implementation :: CPython
Classifier: Operating System :: OS Independent
